bombard/LICENSE.txt
bombard/__init__.py
bombard/__main__.py
bombard/args.py
bombard/attr_dict.py
bombard/bombardier.py
bombard/campaign_yaml.py
bombard/expand_file_name.py
bombard/http_request.py
bombard/main.py
bombard/mock_globals.py
bombard/pretty_ns.py
bombard/pretty_sz.py
bombard/report.py
bombard/request_logging.py
bombard/show_descr.py
bombard/terminal_colours.py
bombard/weaver_mill.py
bombard/examples/README.md
bombard/examples/easy.yaml
bombard/examples/simple.yaml
bombard/examples/simplest.yaml
bombard/examples/simpleton.yaml
tests/__init__.py
tests/fake_args.py
tests/fake_jsonplaceholder.py
tests/stdout_capture.py
tests/test_campaign_check.py
tests/test_doctests.py
tests/test_examples.py
tests/test_http_requests.py
tests/test_init.py
tests/test_report.py
tests/test_show_folder.py
tests/test_supply.py
tests/test_version.py
bombard-1.20.dist-info/LICENSE.txt
bombard-1.20.dist-info/METADATA
bombard-1.20.dist-info/WHEEL
bombard-1.20.dist-info/entry_points.txt
bombard-1.20.dist-info/top_level.txt
bombard-1.20.dist-info/RECORD
