Metadata-Version: 2.1
Name: bombard
Version: 1.20
Summary: Bombards target server with simultaneous requests
Home-page: https://bombard.readthedocs.io/en/latest/
Author: Andrey Sorokin
Author-email: filbert@yandex.ru
License: UNKNOWN
Keywords: http load test parallel
Platform: UNKNOWN
Classifier: Programming Language :: Python :: 3
Classifier: License :: OSI Approved :: MIT License
Classifier: Operating System :: OS Independent
Requires-Dist: pyyaml (>=5.1)
Requires-Dist: pygments
Requires-Dist: colorama
